pydublinbus/__init__.py
pydublinbus/pydublinbus.py
pydublinbus-0.0.4.dist-info/LICENSE.txt
pydublinbus-0.0.4.dist-info/METADATA
pydublinbus-0.0.4.dist-info/WHEEL
pydublinbus-0.0.4.dist-info/top_level.txt
pydublinbus-0.0.4.dist-info/RECORD
