Metadata-Version: 2.1
Name: pydublinbus
Version: 0.0.4
Summary: Python library to get the real-time transport information (RTPI) for Dublin Bus
Home-page: https://github.com/ialex87/pydublinbus
Author: Alex Iepuras
Author-email: iepuras.alex@gmail.com
License: MIT
Download-URL: https://github.com/ialex87/pydublinbus
Keywords: dublin bus RTPI
Platform: any
Requires-Python: >=3.6
Requires-Dist: requests
